BinaryTrees/Node.py
BinaryTrees/__init__.py
BinaryTrees/graphical.py
BinaryTreat-0.0.1.dist-info/LICENSE
BinaryTreat-0.0.1.dist-info/METADATA
BinaryTreat-0.0.1.dist-info/WHEEL
BinaryTreat-0.0.1.dist-info/top_level.txt
BinaryTreat-0.0.1.dist-info/RECORD
