Metadata-Version: 2.1
Name: BinaryTreat
Version: 0.0.1
Summary: A library for showing your binary tree graphically
Author: Amir Sabri
Author-email: amirsbry1942@gmail.com
License-File: LICENSE
